Metadata-Version: 1.0
Name: coind
Version: 1.0.0
Summary: A bitcoind based wallet manager in Python
Home-page: https://github.com/cryptch/coind
Author: Cryptch
Author-email: fukuroh1@gmail.com
License: MIT
Keywords: coind,bitcoin,bitcoind,crypto,cryptch
Platform: UNKNOWN
